coord2loc_can/__init__.py
coord2loc_can/py.typed
coord2loc_can/data/__init__.py
coord2loc_can/data/meta.msgpack
coord2loc_can/data/polygons.msgpack
coord2loc_can-0.0.1.dist-info/METADATA
coord2loc_can-0.0.1.dist-info/WHEEL
coord2loc_can-0.0.1.dist-info/entry_points.txt
coord2loc_can-0.0.1.dist-info/RECORD
